{
  "plan": "basic-rp",
  "plan_id": "k14GyYkholz4l",
  "suite_url": "https://localhost.emobix.co.uk:8443",
  "results": [
    {
      "test": "oidcc-client-test",
      "status": "PASSED",
      "test_id": "qAV7nbRtxkI4c40",
      "log_url": "https://localhost.emobix.co.uk:8443/log-detail.html?log=qAV7nbRtxkI4c40",
      "detail": ""
    },
    {
      "test": "oidcc-client-test-invalid-iss",
      "status": "PASSED",
      "test_id": "EtKLH4AXQe4Uh0n",
      "log_url": "https://localhost.emobix.co.uk:8443/log-detail.html?log=EtKLH4AXQe4Uh0n",
      "detail": ""
    },
    {
      "test": "oidcc-client-test-missing-sub",
      "status": "PASSED",
      "test_id": "dumfCr7PFyQP10b",
      "log_url": "https://localhost.emobix.co.uk:8443/log-detail.html?log=dumfCr7PFyQP10b",
      "detail": ""
    },
    {
      "test": "oidcc-client-test-invalid-aud",
      "status": "PASSED",
      "test_id": "c5kOspGFCSX3L2v",
      "log_url": "https://localhost.emobix.co.uk:8443/log-detail.html?log=c5kOspGFCSX3L2v",
      "detail": ""
    },
    {
      "test": "oidcc-client-test-missing-iat",
      "status": "PASSED",
      "test_id": "5BwxiEdKzRHEbbx",
      "log_url": "https://localhost.emobix.co.uk:8443/log-detail.html?log=5BwxiEdKzRHEbbx",
      "detail": ""
    },
    {
      "test": "oidcc-client-test-kid-absent-single-jwks",
      "status": "PASSED",
      "test_id": "Uw4Vo06HGj64KAA",
      "log_url": "https://localhost.emobix.co.uk:8443/log-detail.html?log=Uw4Vo06HGj64KAA",
      "detail": ""
    },
    {
      "test": "oidcc-client-test-kid-absent-multiple-jwks",
      "status": "PASSED",
      "test_id": "UTBbYd6j3zh7mzd",
      "log_url": "https://localhost.emobix.co.uk:8443/log-detail.html?log=UTBbYd6j3zh7mzd",
      "detail": ""
    },
    {
      "test": "oidcc-client-test-idtoken-sig-rs256",
      "status": "PASSED",
      "test_id": "teLrnYICPG6ueEx",
      "log_url": "https://localhost.emobix.co.uk:8443/log-detail.html?log=teLrnYICPG6ueEx",
      "detail": ""
    },
    {
      "test": "oidcc-client-test-idtoken-sig-none",
      "status": "SKIPPED",
      "test_id": "IlMch9Tv777LU8u",
      "log_url": "https://localhost.emobix.co.uk:8443/log-detail.html?log=IlMch9Tv777LU8u",
      "detail": ""
    },
    {
      "test": "oidcc-client-test-invalid-sig-rs256",
      "status": "PASSED",
      "test_id": "ipGQGlIKJh2JQB6",
      "log_url": "https://localhost.emobix.co.uk:8443/log-detail.html?log=ipGQGlIKJh2JQB6",
      "detail": ""
    },
    {
      "test": "oidcc-client-test-userinfo-invalid-sub",
      "status": "PASSED",
      "test_id": "BsbyPguPrxeh1iF",
      "log_url": "https://localhost.emobix.co.uk:8443/log-detail.html?log=BsbyPguPrxeh1iF",
      "detail": ""
    },
    {
      "test": "oidcc-client-test-nonce-invalid",
      "status": "PASSED",
      "test_id": "1vKdDNwdbM00S4I",
      "log_url": "https://localhost.emobix.co.uk:8443/log-detail.html?log=1vKdDNwdbM00S4I",
      "detail": ""
    },
    {
      "test": "oidcc-client-test-scope-userinfo-claims",
      "status": "PASSED",
      "test_id": "tEHWC2dSRVFxU0X",
      "log_url": "https://localhost.emobix.co.uk:8443/log-detail.html?log=tEHWC2dSRVFxU0X",
      "detail": ""
    },
    {
      "test": "oidcc-client-test-client-secret-basic",
      "status": "PASSED",
      "test_id": "oBKNnHtBiVF7TcP",
      "log_url": "https://localhost.emobix.co.uk:8443/log-detail.html?log=oBKNnHtBiVF7TcP",
      "detail": ""
    }
  ],
  "summary": {
    "total": 14,
    "passed": 13,
    "warning": 0,
    "failed": 0,
    "review": 0,
    "skipped": 1
  },
  "all_passed": true
}
